LICENSE.txt
MANIFEST.in
README.txt
setup.py
TesseractTrainer.egg-info/PKG-INFO
TesseractTrainer.egg-info/SOURCES.txt
TesseractTrainer.egg-info/dependency_links.txt
TesseractTrainer.egg-info/requires.txt
TesseractTrainer.egg-info/top_level.txt
tesseract_trainer/__init__.py
tesseract_trainer/multipage_tif.py
tesseract_trainer/tesstrain
test/test_tesseract_trainer.py