Metadata-Version: 1.1
Name: TesseractTrainer
Version: 0.1
Summary: A small framework taking over the manual tesseract training process described in the Tesseract Wiki
Home-page: https://github.com/BaltoRouberol/TesseractTrainer
Author: Balthazar Rouberol
Author-email: rouberol.b@gmail.com
License: # FreeBSD license
